bibverify/__init__.py
bibverify/cli.py
bibverify-0.1.0.dist-info/licenses/LICENSE
bibverify-0.1.0.dist-info/METADATA
bibverify-0.1.0.dist-info/WHEEL
bibverify-0.1.0.dist-info/entry_points.txt
bibverify-0.1.0.dist-info/top_level.txt
bibverify-0.1.0.dist-info/RECORD
