Metadata-Version: 2.4
Name: bibverify
Version: 0.1.0
Summary: Bibverify: A Multi-Platform BibTeX Reference Verification Tool
Author: Hong Liu
License: MIT License
Project-URL: Homepage, https://github.com/Hylouis233/bibverify
Project-URL: Repository, https://github.com/Hylouis233/bibverify
Project-URL: Issues, https://github.com/Hylouis233/bibverify/issues
Keywords: bibtex,reference,citation,crossref,openalex,academic
Classifier: Programming Language :: Python :: 3
Classifier: License :: OSI Approved :: MIT License
Classifier: Operating System :: OS Independent
Requires-Python: >=3.7
License-File: LICENSE
Requires-Dist: bibtexparser>=1.4.0
Requires-Dist: requests>=2.28.0
Dynamic: license-file
